{
"type": "FeatureCollection",
"name": "unoise-02",
"crs": { "type": "name", "properties": { "name": "urn:ogc:def:crs:OGC:1.3:CRS84" } },
"features": [
{ "type": "Feature", "properties": { "fid": 1, "Name": "St2019[W][ITRTtest][CAcoustics]_OWF-S1_replace", "station": "OWF-S1", "Y": 24.66771, "X": 120.77193, "F5": "24° 40' 3.78\"", "F6": "120° 46' 18.96\"", "pre_dev": 1 }, "geometry": { "type": "Point", "coordinates": [ 120.77193, 24.66771 ] } },
{ "type": "Feature", "properties": { "fid": 2, "Name": "St2019[W][ITRTtest][CAcoustics]_OWF-S4_replace", "station": "OWF-S4", "Y": 24.72291, "X": 120.8558, "F5": "24° 43' 22.5\"", "F6": "120° 51' 20.9\"", "pre_dev": 1 }, "geometry": { "type": "Point", "coordinates": [ 120.8558, 24.72291 ] } },
{ "type": "Feature", "properties": { "fid": 3, "Name": "St2019[W][ITRTtest][CAcoustics]_OWF-S5_replace", "station": "OWF-S5", "Y": 24.67079, "X": 120.78485, "F5": "24° 40' 14.87\"", "F6": "120° 47' 5.46", "pre_dev": 1 }, "geometry": { "type": "Point", "coordinates": [ 120.78485, 24.67079 ] } }
]
}
